{
    "Fratboy" : {
        "actions": ["Take a shot","Show up late", "Haze", "Hydrate"],
        "items": [ "Computer", "Beanie"]
    },
    "CSESophomore": {
        "actions": ["Throw class materials", "Study", "Caffienate", "Cry"],
        "items": ["Book"]
    },
    "Techie" : {
        "actions": ["Humble brag", "Consult Stack Overflow", "Snarky remark", "Adjust tie"],
        "items": ["Book", "Computer", "Suit and Tie", "Converse", "Beanie"]
    },
    "Terror": {
        "actions": ["Bite", "Honk", "Screech", "Poop"],
        "items": ["Book", "Computer"]
    }

}